setup.py
data-checks/__init__.py
data-checks/data_checker.py
data-checks/data_types.py
data-checks/database_operations.py
data-checks/duplicates.py
data-checks/missing_values.py
propreturns_data_checker.egg-info/PKG-INFO
propreturns_data_checker.egg-info/SOURCES.txt
propreturns_data_checker.egg-info/dependency_links.txt
propreturns_data_checker.egg-info/requires.txt
propreturns_data_checker.egg-info/top_level.txt
slack/__init__.py
slack/slack_operations.py
utils/__init__.py
utils/common_utils.py